Metadata-Version: 1.0
Name: vvs25-distributions
Version: 0.1
Summary: Gaussian distributions
Home-page: UNKNOWN
Author: Varun Vinod Salian
Author-email: salianvarun30@gmail.com
License: UNKNOWN
Platform: UNKNOWN
